{"amendement": {"@xmlns": "http://schemas.assemblee-nationale.fr/referentiel", "uid": "AMANR5L16PO791932BTC2600P0D1N004983", "chronotag": "1715864511013", "legislature": "16", "identification": {"numeroLong": "4983", "numeroOrdreDepot": "4983", "prefixeOrganeExamen": "AN", "numeroRect": "0"}, "examenRef": "EXANR5L16PO791932BTC2600P0D1", "texteLegislatifRef": "PRJLANR5L16BTC2600", "triAmendement": "acaaaaaaaaaaaaaaaaaaaaaaaaaaaaaaaaaaaaaaaaaaaaaaaabzlkxw", "cardinaliteAmdtMultiples": "1", "amendementParentRef": "AMANR5L16PO791932BTC2600P0D1N003952", "signataires": {"auteur": {"typeAuteur": "D\u00e9put\u00e9", "gouvernementRef": {"@xmlns:xsi": "http://www.w3.org/2001/XMLSchema-instance", "@xsi:nil": "true"}, "acteurRef": "PA721046", "groupePolitiqueRef": "PO800532", "auteurRapporteurOrganeRef": {"@xmlns:xsi": "http://www.w3.org/2001/XMLSchema-instance", "@xsi:nil": "true"}}, "cosignataires": {"acteurRef": ["PA719146", "PA267766", "PA605069", "PA719138", "PA719286", "PA267042", "PA822617", "PA795244", "PA720976", "PA607619", "PA266788", "PA721486", "PA333421", "PA793210", "PA794626", "PA2952", "PA942", "PA793796"]}, "suffixe": {"@xmlns:xsi": "http://www.w3.org/2001/XMLSchema-instance", "@xsi:nil": "true"}, "libelle": "Mme&#160;Bassire,  M.&#160;Acquaviva, M.&#160;Guy&#160;Bricout, M.&#160;Jean-Louis&#160;Bricout, M.&#160;Castellani, M.&#160;Colombani, M.&#160;Favennec-B&#233;cot&#160;, Mme&#160;Froger, M.&#160;Lenormand, M.&#160;Mathiasin, M.&#160;Molac, M.&#160;Morel-&#192;-L&apos;Huissier, M.&#160;Naegelen, M.&#160;Pancher, M.&#160;Panifous, M.&#160;Saint-Huile, M.&#160;Warsmann, M.&#160;de&#160;Courson et M.&#160;Taupiac"}, "pointeurFragmentTexte": {"partieAmendableRef": {"@xmlns:xsi": "http://www.w3.org/2001/XMLSchema-instance", "@xsi:nil": "true"}, "division": {"titre": "Article PREMIER", "articleDesignationCourte": "ART. PREMIER", "articleDesignation": "ARTICLE PREMIER", "type": "ARTICLE", "avant_A_Apres": "A", "divisionRattachee": {"@xmlns:xsi": "http://www.w3.org/2001/XMLSchema-instance", "@xsi:nil": "true"}, "articleAdditionnel": "false", "chapitreAdditionnel": "false", "urlDivisionTexteVise": "/16/textes/2600.asp#D_Article_1er"}, "amendementStandard": {"alinea": {"@xmlns:xsi": "http://www.w3.org/2001/XMLSchema-instance", "@xsi:nil": "true"}}}, "corps": {"cartoucheInformatif": {"@xmlns:xsi": "http://www.w3.org/2001/XMLSchema-instance", "@xsi:nil": "true"}, "contenuAuteur": {"dispositif": "<p style=\"text-align: justify;\">I. &#x2013; apr&#x00E8;s l&#x2019;alin&#x00E9;a&nbsp;14, ins&#x00E9;rer l&#x2019;alin&#x00E9;a suivant&nbsp;:</p><p style=\"text-align: justify;\">&#x00AB;&nbsp;&#x00AB;&nbsp;II <i>bis</i>. &#x2013; A&#x0300; compter de la promulgation de la loi, puis tous les dix ans, la loi d&#x2019;orientation de l&#x2019;agriculture franc&#x0327;aise a pour objectif, dans le cadre de la politique e&#x0301;conomique, sociale et environnementale, de contribuer au de&#x0301;veloppement du secteur agricole et a&#x0300; l&#x2019;innovation.&nbsp;&#x00BB;</p><p style=\"text-align: justify;\">II. En cons&#x00E9;quence, &#x00E0; l&#x2019;alin&#x00E9;a&nbsp;15, apr&#x00E8;s la premi&#x00E8;re occurrence du mot&nbsp;:&nbsp;</p><p style=\"text-align: justify;\">&#x00AB;&nbsp;agriculture&nbsp;&#x00BB;,</p><p style=\"text-align: justify;\">ins&#x00E9;rer les mots&nbsp;:&nbsp;</p><p style=\"text-align: justify;\">&#x00AB;&nbsp;, fix&#x00E9;e par d&#x00E9;cret&nbsp;&#x00BB;.</p><p style=\"text-align: justify;\">III. Compl&#x00E9;ter le m&#x00EA;me alin&#x00E9;a par les mots&nbsp;:&nbsp;</p><p style=\"text-align: justify;\">&#x00AB;&nbsp;La Corse, la Nouvelle-Cale&#x0301;donie et les collectivite&#x0301;s re&#x0301;gies par les articles 73 et 74 de la Constitution font chacune l&#x2019;objet d&#x2019;une programmation pluriannuelle distincte.&nbsp;&#x00BB;</p>", "avantAppel": {"@xmlns:xsi": "http://www.w3.org/2001/XMLSchema-instance", "@xsi:nil": "true"}, "exposeSommaire": "<p style=\"text-align: justify;\">Cet amendement appelle a&#x0300; l'adoption d'une loi d'orientation agricole, tous les dix ans, ainsi que d'un de&#x0301;cret fixant une programmation pluriannuelle de l'agriculture. Ils demandent en outre, que les Outre-mer et la Corse se dotent de programmation spe&#x0301;cifiques, a&#x0300; l'instar de ce qui est pre&#x0301;vu pour les programmations pluriannuelles de l'e&#x0301;nergie.</p>", "annexeExposeSommaire": {"@xmlns:xsi": "http://www.w3.org/2001/XMLSchema-instance", "@xsi:nil": "true"}}}, "cycleDeVie": {"dateDepot": "2024-05-14", "datePublication": "2024-05-15", "soumisArticle40": "false", "etatDesTraitements": {"etat": {"code": "DI", "libelle": "Discut\u00e9"}, "sousEtat": {"code": "DI", "libelle": "Non soutenu"}}, "dateSort": "2024-05-16T15:01:39+02:00", "sort": "Non soutenu"}, "representations": {"representation": {"nom": "PDF", "typeMime": {"type": "application", "subType": "PDF"}, "statutRepresentation": {"verbatim": "true", "canonique": "true", "officielle": "true", "transcription": "false", "enregistrement": "false"}, "repSource": {"@xmlns:xsi": "http://www.w3.org/2001/XMLSchema-instance", "@xsi:nil": "true"}, "offset": {"@xmlns:xsi": "http://www.w3.org/2001/XMLSchema-instance", "@xsi:nil": "true"}, "contenu": {"documentURI": "/base/AMANR5L16PO791932BTC2600P0D1N004983?format=pdf"}, "dateDispoRepresentation": {"@xmlns:xsi": "http://www.w3.org/2001/XMLSchema-instance", "@xsi:nil": "true"}}}, "seanceDiscussionRef": "RUANR5L16S2024IDS28360", "article99": "false", "loiReference": {"codeLoi": "ap 14", "divisionCodeLoi": {"@xmlns:xsi": "http://www.w3.org/2001/XMLSchema-instance", "@xsi:nil": "true"}}, "discussionCommune": {"@xmlns:xsi": "http://www.w3.org/2001/XMLSchema-instance", "@xsi:nil": "true"}, "discussionIdentique": {"@xmlns:xsi": "http://www.w3.org/2001/XMLSchema-instance", "@xsi:nil": "true"}, "accordGouvernementDepotHorsDelai": "Sans objet"}}