{"amendement": {"@xmlns": "http://schemas.assemblee-nationale.fr/referentiel", "uid": "AMANR5L16PO791932BTC2600P0D1N005252", "chronotag": "1715894571076", "legislature": "16", "identification": {"numeroLong": "5252", "numeroOrdreDepot": "5252", "prefixeOrganeExamen": "AN", "numeroRect": "0"}, "examenRef": "EXANR5L16PO791932BTC2600P0D1", "texteLegislatifRef": "PRJLANR5L16BTC2600", "triAmendement": "acaaaaaaaaaaaaaaaaaaaaaaaaaaaaaaaaaaaaaaaaaaaaaaaabzlibderzx", "cardinaliteAmdtMultiples": "1", "amendementParentRef": "AMANR5L16PO791932BTC2600P0D1N003952", "signataires": {"auteur": {"typeAuteur": "D\u00e9put\u00e9", "gouvernementRef": {"@xmlns:xsi": "http://www.w3.org/2001/XMLSchema-instance", "@xsi:nil": "true"}, "acteurRef": "PA794082", "groupePolitiqueRef": "PO800490", "auteurRapporteurOrganeRef": {"@xmlns:xsi": "http://www.w3.org/2001/XMLSchema-instance", "@xsi:nil": "true"}}, "cosignataires": {"@xmlns:xsi": "http://www.w3.org/2001/XMLSchema-instance", "@xsi:nil": "true"}, "suffixe": {"@xmlns:xsi": "http://www.w3.org/2001/XMLSchema-instance", "@xsi:nil": "true"}, "libelle": "Mme&#160;Hignet"}, "pointeurFragmentTexte": {"partieAmendableRef": {"@xmlns:xsi": "http://www.w3.org/2001/XMLSchema-instance", "@xsi:nil": "true"}, "division": {"titre": "Article PREMIER", "articleDesignationCourte": "ART. PREMIER", "articleDesignation": "ARTICLE PREMIER", "type": "ARTICLE", "avant_A_Apres": "A", "divisionRattachee": {"@xmlns:xsi": "http://www.w3.org/2001/XMLSchema-instance", "@xsi:nil": "true"}, "articleAdditionnel": "false", "chapitreAdditionnel": "false", "urlDivisionTexteVise": "/16/textes/2600.asp#D_Article_1er"}, "amendementStandard": {"alinea": {"@xmlns:xsi": "http://www.w3.org/2001/XMLSchema-instance", "@xsi:nil": "true"}}}, "corps": {"cartoucheInformatif": {"@xmlns:xsi": "http://www.w3.org/2001/XMLSchema-instance", "@xsi:nil": "true"}, "contenuAuteur": {"dispositif": "<p style=\"text-align: justify;\">&#x00C0; l&#x2019;alin&#x00E9;a&nbsp;7, substituer aux mots&nbsp;:</p><p style=\"text-align: justify;\">&#x00AB;&nbsp;d&#x00E9;capitalisation de l&#x2019;&#x00E9;levage&nbsp;&#x00BB;,&nbsp;</p><p style=\"text-align: justify;\">les mots&nbsp;:</p><p style=\"text-align: justify;\">&#x00AB;&nbsp;diminution du nombre d&#x2019;&#x00E9;leveurs&nbsp;&#x00BB;.</p>", "avantAppel": {"@xmlns:xsi": "http://www.w3.org/2001/XMLSchema-instance", "@xsi:nil": "true"}, "exposeSommaire": "<p style=\"text-align: justify;\">\"Par cet amendement, le groupe LFI-NUPES souhaite remplacer la lutte contre la d&#x00E9;capitalisation de l'&#x00E9;levage par la lutte contre la diminution du nombre d'&#x00E9;leveurs.</p><p>Le probl&#x00E8;me r&#x00E9;side avant tout dans la forte diminution du nombre d'&#x00E9;leveurs en France. Comme le r&#x00E9;v&#x00E8;le la France Agricole dans un article paru le 28 d&#x00E9;cembre 2022 concernant l'&#x00E9;levage porcins : entre 2010 et 2020, le cheptel porcin fran&#x00E7;ais n'a diminu&#x00E9; que de 3,5 %. Par contre, le nombre d'&#x00E9;leveurs porcins &#x00E0; quant &#x00E0; lui &#x00E9;t&#x00E9; divis&#x00E9; par 2.</p><p>Nous devons donc avant tout lutter contre la diminution du nombre d'&#x00E9;leveurs, en favorisation notamment la restructuration-diversification des exploitations agricoles.\"</p>", "annexeExposeSommaire": {"@xmlns:xsi": "http://www.w3.org/2001/XMLSchema-instance", "@xsi:nil": "true"}}}, "cycleDeVie": {"dateDepot": "2024-05-15", "datePublication": "2024-05-15", "soumisArticle40": "false", "etatDesTraitements": {"etat": {"code": "DI", "libelle": "Discut\u00e9"}, "sousEtat": {"code": "DI", "libelle": "Rejet\u00e9"}}, "dateSort": "2024-05-16T23:22:40+02:00", "sort": "Rejet\u00e9"}, "representations": {"representation": {"nom": "PDF", "typeMime": {"type": "application", "subType": "PDF"}, "statutRepresentation": {"verbatim": "true", "canonique": "true", "officielle": "true", "transcription": "false", "enregistrement": "false"}, "repSource": {"@xmlns:xsi": "http://www.w3.org/2001/XMLSchema-instance", "@xsi:nil": "true"}, "offset": {"@xmlns:xsi": "http://www.w3.org/2001/XMLSchema-instance", "@xsi:nil": "true"}, "contenu": {"documentURI": "/base/AMANR5L16PO791932BTC2600P0D1N005252?format=pdf"}, "dateDispoRepresentation": {"@xmlns:xsi": "http://www.w3.org/2001/XMLSchema-instance", "@xsi:nil": "true"}}}, "seanceDiscussionRef": "RUANR5L16S2024IDS28361", "article99": "false", "loiReference": {"codeLoi": "7", "divisionCodeLoi": {"@xmlns:xsi": "http://www.w3.org/2001/XMLSchema-instance", "@xsi:nil": "true"}}, "discussionCommune": {"@xmlns:xsi": "http://www.w3.org/2001/XMLSchema-instance", "@xsi:nil": "true"}, "discussionIdentique": {"idDiscussion": "70587", "typePosition": "Premier"}, "accordGouvernementDepotHorsDelai": "Sans objet"}}