{"amendement": {"@xmlns": "http://schemas.assemblee-nationale.fr/referentiel", "uid": "AMANR5L16PO791932BTC2600P0D1N005276", "chronotag": "1715896671176", "legislature": "16", "identification": {"numeroLong": "5276", "numeroOrdreDepot": "5276", "prefixeOrganeExamen": "AN", "numeroRect": "0"}, "examenRef": "EXANR5L16PO791932BTC2600P0D1", "texteLegislatifRef": "PRJLANR5L16BTC2600", "triAmendement": "acaaaaaaaaaaaaaaaaaaaaaaaaaaaaaaaaaaaaaaaaaaaaaaaabzllqwm", "cardinaliteAmdtMultiples": "1", "amendementParentRef": "AMANR5L16PO791932BTC2600P0D1N003952", "signataires": {"auteur": {"typeAuteur": "D\u00e9put\u00e9", "gouvernementRef": {"@xmlns:xsi": "http://www.w3.org/2001/XMLSchema-instance", "@xsi:nil": "true"}, "acteurRef": "PA266788", "groupePolitiqueRef": "PO800532", "auteurRapporteurOrganeRef": {"@xmlns:xsi": "http://www.w3.org/2001/XMLSchema-instance", "@xsi:nil": "true"}}, "cosignataires": {"acteurRef": ["PA719146", "PA721046", "PA267766", "PA605069", "PA719138", "PA719286", "PA942", "PA720696", "PA267042", "PA822617", "PA795244", "PA720976", "PA607619", "PA721486", "PA333421", "PA793210", "PA794626", "PA793796", "PA2952"]}, "suffixe": {"@xmlns:xsi": "http://www.w3.org/2001/XMLSchema-instance", "@xsi:nil": "true"}, "libelle": "M.&#160;Morel-&#192;-L&apos;Huissier,  M.&#160;Acquaviva, Mme&#160;Bassire, M.&#160;Guy&#160;Bricout, M.&#160;Jean-Louis&#160;Bricout, M.&#160;Castellani, M.&#160;Colombani, M.&#160;de&#160;Courson, Mme&#160;Descamps, M.&#160;Favennec-B&#233;cot&#160;, Mme&#160;Froger, M.&#160;Lenormand, M.&#160;Mathiasin, M.&#160;Molac, M.&#160;Naegelen, M.&#160;Pancher, M.&#160;Panifous, M.&#160;Saint-Huile, M.&#160;Taupiac et M.&#160;Warsmann"}, "pointeurFragmentTexte": {"partieAmendableRef": {"@xmlns:xsi": "http://www.w3.org/2001/XMLSchema-instance", "@xsi:nil": "true"}, "division": {"titre": "Article PREMIER", "articleDesignationCourte": "ART. PREMIER", "articleDesignation": "ARTICLE PREMIER", "type": "ARTICLE", "avant_A_Apres": "A", "divisionRattachee": {"@xmlns:xsi": "http://www.w3.org/2001/XMLSchema-instance", "@xsi:nil": "true"}, "articleAdditionnel": "false", "chapitreAdditionnel": "false", "urlDivisionTexteVise": "/16/textes/2600.asp#D_Article_1er"}, "amendementStandard": {"alinea": {"@xmlns:xsi": "http://www.w3.org/2001/XMLSchema-instance", "@xsi:nil": "true"}}}, "corps": {"cartoucheInformatif": {"@xmlns:xsi": "http://www.w3.org/2001/XMLSchema-instance", "@xsi:nil": "true"}, "contenuAuteur": {"dispositif": "<p style=\"text-align: justify;\">&#x00C0; l&#x2019;alin&#x00E9;a&nbsp;23, apr&#x00E8;s la seconde occurrence du mot :&nbsp;</p><p style=\"text-align: justify;\">&#x00AB;&nbsp;&#x00E9;levage&nbsp;&#x00BB;,&nbsp;</p><p style=\"text-align: justify;\">ins&#x00E9;rer les mots&nbsp;:&nbsp;</p><p style=\"text-align: justify;\">&#x00AB;&nbsp;de soutenir le d&#x00E9;veloppement de l&#x2019;&#x00E9;levage en p&#x00E2;turage, et de garantir les moyens de sa protection&nbsp;;&nbsp;&#x00BB;.</p>", "avantAppel": {"@xmlns:xsi": "http://www.w3.org/2001/XMLSchema-instance", "@xsi:nil": "true"}, "exposeSommaire": "<p style=\"text-align: justify;\">Ce sous-amendement vise &#x00E0; soutenir l'&#x00E9;levage en p&#x00E2;turage. Ce mode d'&#x00E9;levage,&nbsp;respectueux de l'environnement, pr&#x00E9;sente &#x00E9;galement des b&#x00E9;n&#x00E9;fices sur le bien-&#x00EA;tre animal et joue un r&#x00F4;le d&#x00E9;terminant d'am&#x00E9;nagement dans la ruralit&#x00E9;.&nbsp;</p><p>Les auteurs de ce sous-amendement appellent notamment &#x00E0; :&nbsp;</p><p>&nbsp;- ouvrir&nbsp;le champ des esp&#x00E8;ces admises au p&#x00E2;turage, pour y inclure les caprins, les lamas et les alpaga;&nbsp;</p><p>- Mieux prot&#x00E9;ger le b&#x00E9;tails et donc d&#x2019;am&#x00E9;liorer la lutte contre la pr&#x00E9;dation des loups, en&nbsp;renfor&#x00E7;ant les lieutenants de louverie et en g&#x00E9;n&#x00E9;ralisant les brigades loups.</p>", "annexeExposeSommaire": {"@xmlns:xsi": "http://www.w3.org/2001/XMLSchema-instance", "@xsi:nil": "true"}}}, "cycleDeVie": {"dateDepot": "2024-05-15", "datePublication": "2024-05-15", "soumisArticle40": "false", "etatDesTraitements": {"etat": {"code": "DI", "libelle": "Discut\u00e9"}, "sousEtat": {"code": "DI", "libelle": "Rejet\u00e9"}}, "dateSort": "2024-05-16T23:57:43+02:00", "sort": "Rejet\u00e9"}, "representations": {"representation": {"nom": "PDF", "typeMime": {"type": "application", "subType": "PDF"}, "statutRepresentation": {"verbatim": "true", "canonique": "true", "officielle": "true", "transcription": "false", "enregistrement": "false"}, "repSource": {"@xmlns:xsi": "http://www.w3.org/2001/XMLSchema-instance", "@xsi:nil": "true"}, "offset": {"@xmlns:xsi": "http://www.w3.org/2001/XMLSchema-instance", "@xsi:nil": "true"}, "contenu": {"documentURI": "/base/AMANR5L16PO791932BTC2600P0D1N005276?format=pdf"}, "dateDispoRepresentation": {"@xmlns:xsi": "http://www.w3.org/2001/XMLSchema-instance", "@xsi:nil": "true"}}}, "seanceDiscussionRef": "RUANR5L16S2024IDS28361", "article99": "false", "loiReference": {"codeLoi": "24", "divisionCodeLoi": {"@xmlns:xsi": "http://www.w3.org/2001/XMLSchema-instance", "@xsi:nil": "true"}}, "discussionCommune": {"@xmlns:xsi": "http://www.w3.org/2001/XMLSchema-instance", "@xsi:nil": "true"}, "discussionIdentique": {"@xmlns:xsi": "http://www.w3.org/2001/XMLSchema-instance", "@xsi:nil": "true"}, "accordGouvernementDepotHorsDelai": "Sans objet"}}