{"amendement": {"@xmlns": "http://schemas.assemblee-nationale.fr/referentiel", "uid": "AMANR5L16PO791932BTC2600P0D1N004429", "chronotag": "1716488697846", "legislature": "16", "identification": {"numeroLong": "4429", "numeroOrdreDepot": "4429", "prefixeOrganeExamen": "AN", "numeroRect": "0"}, "examenRef": "EXANR5L16PO791932BTC2600P0D1", "texteLegislatifRef": "PRJLANR5L16BTC2600", "triAmendement": "eeaaaaaaaaaaaaaaaaaaaaaaaaaaaaaaaaaaaaaaaaaaaaaaaadyi", "cardinaliteAmdtMultiples": "1", "amendementParentRef": {"@xmlns:xsi": "http://www.w3.org/2001/XMLSchema-instance", "@xsi:nil": "true"}, "signataires": {"auteur": {"typeAuteur": "D\u00e9put\u00e9", "gouvernementRef": {"@xmlns:xsi": "http://www.w3.org/2001/XMLSchema-instance", "@xsi:nil": "true"}, "acteurRef": "PA719822", "groupePolitiqueRef": "PO800484", "auteurRapporteurOrganeRef": {"@xmlns:xsi": "http://www.w3.org/2001/XMLSchema-instance", "@xsi:nil": "true"}}, "cosignataires": {"acteurRef": "PA719640"}, "suffixe": {"@xmlns:xsi": "http://www.w3.org/2001/XMLSchema-instance", "@xsi:nil": "true"}, "libelle": "Mme&#160;Thillaye et Mme&#160;Mette"}, "pointeurFragmentTexte": {"partieAmendableRef": {"@xmlns:xsi": "http://www.w3.org/2001/XMLSchema-instance", "@xsi:nil": "true"}, "division": {"titre": "Article 9", "articleDesignationCourte": "ART. 9", "articleDesignation": "ARTICLE 9", "type": "ARTICLE", "avant_A_Apres": "A", "divisionRattachee": {"@xmlns:xsi": "http://www.w3.org/2001/XMLSchema-instance", "@xsi:nil": "true"}, "articleAdditionnel": "false", "chapitreAdditionnel": "false", "urlDivisionTexteVise": "/16/textes/2600.asp#D_Article_9"}, "amendementStandard": {"alinea": {"avant_A_Apres": {"@xmlns:xsi": "http://www.w3.org/2001/XMLSchema-instance", "@xsi:nil": "true"}, "numero": "2", "alineaDesignation": "Alin\u00e9a 2"}}}, "corps": {"cartoucheInformatif": {"@xmlns:xsi": "http://www.w3.org/2001/XMLSchema-instance", "@xsi:nil": "true"}, "contenuAuteur": {"dispositif": "<p style=\"text-align: justify;\">&#x00C0; la seconde phrase de l&#x2019;alin&#x00E9;a&nbsp;2, apr&#x00E8;s le mot&nbsp;:</p><p style=\"text-align: justify;\">&#x00AB;&nbsp;vie&nbsp;&#x00BB;,&nbsp;</p><p style=\"text-align: justify;\">ins&#x00E9;rer les mots&nbsp;:</p><p style=\"text-align: justify;\">&#x00AB;&nbsp;, y compris pour r&#x00E9;pondre &#x00E0; des enjeux de coop&#x00E9;ration et de mutualisation,&nbsp;&#x00BB;.</p>", "avantAppel": {"@xmlns:xsi": "http://www.w3.org/2001/XMLSchema-instance", "@xsi:nil": "true"}, "exposeSommaire": "<p style=\"text-align: justify;\">Pour de nombreux agriculteurs, la mutualisation est une opportunit&#x00E9; de r&#x00E9;duire les co&#x00FB;ts et d&#x2019;augmenter la productivit&#x00E9;, tout en renfor&#x00E7;ant leur expertise m&#x00E9;tier et en brisant la solitude. Elle est par ailleurs une des r&#x00E9;ponses possibles &#x00E0; la lutte contre l&#x2019;agrandissement d&#x00E9;mesur&#x00E9; des exploitations, et s&#x2019;inscrit donc en faveur de l&#x2019;installation de nouveaux exploitants. C&#x2019;est pourquoi il semble important, lorsque cela est pertinent, d&#x2019;encourager le d&#x00E9;veloppement du mutualisme et de la coop&#x00E9;ration. A la fois en prodiguant, dans le cadre des diagnostics institu&#x00E9;s par cet article, des conseils op&#x00E9;rationnels aux exploitants et en leur fournissant les donn&#x00E9;es juridiques qui leur permettront de contractualiser pour mener leur projet &#x00E0; bien.</p>", "annexeExposeSommaire": {"@xmlns:xsi": "http://www.w3.org/2001/XMLSchema-instance", "@xsi:nil": "true"}}}, "cycleDeVie": {"dateDepot": "2024-05-10", "datePublication": "2024-05-17", "soumisArticle40": "false", "etatDesTraitements": {"etat": {"code": "DI", "libelle": "Discut\u00e9"}, "sousEtat": {"code": "DI", "libelle": "Tomb\u00e9"}}, "dateSort": "2024-05-23T20:24:49+02:00", "sort": "Tomb\u00e9"}, "representations": {"representation": {"nom": "PDF", "typeMime": {"type": "application", "subType": "PDF"}, "statutRepresentation": {"verbatim": "true", "canonique": "true", "officielle": "true", "transcription": "false", "enregistrement": "false"}, "repSource": {"@xmlns:xsi": "http://www.w3.org/2001/XMLSchema-instance", "@xsi:nil": "true"}, "offset": {"@xmlns:xsi": "http://www.w3.org/2001/XMLSchema-instance", "@xsi:nil": "true"}, "contenu": {"documentURI": "/base/AMANR5L16PO791932BTC2600P0D1N004429?format=pdf"}, "dateDispoRepresentation": {"@xmlns:xsi": "http://www.w3.org/2001/XMLSchema-instance", "@xsi:nil": "true"}}}, "seanceDiscussionRef": "RUANR5L16S2024IDS28370", "article99": "false", "loiReference": {"codeLoi": "2", "divisionCodeLoi": {"@xmlns:xsi": "http://www.w3.org/2001/XMLSchema-instance", "@xsi:nil": "true"}}, "discussionCommune": {"@xmlns:xsi": "http://www.w3.org/2001/XMLSchema-instance", "@xsi:nil": "true"}, "discussionIdentique": {"@xmlns:xsi": "http://www.w3.org/2001/XMLSchema-instance", "@xsi:nil": "true"}, "accordGouvernementDepotHorsDelai": "Sans objet"}}