{"amendement": {"@xmlns": "http://schemas.assemblee-nationale.fr/referentiel", "uid": "AMANR5L16PO419610B2436P0D1N000840", "chronotag": "1714818563430", "legislature": "16", "identification": {"numeroLong": "CE840", "numeroOrdreDepot": "840", "prefixeOrganeExamen": "CION-ECO", "numeroRect": "0"}, "examenRef": "EXANR5L16PO419610B2436P0D1", "texteLegislatifRef": "PRJLANR5L16B2436", "triAmendement": "jiaaaaaaaaaaaaaaaaaaaaaaaaaaaaaaaaaaaaaaaaaaaaaaaanypzzs", "cardinaliteAmdtMultiples": "1", "amendementParentRef": {"@xmlns:xsi": "http://www.w3.org/2001/XMLSchema-instance", "@xsi:nil": "true"}, "signataires": {"auteur": {"typeAuteur": "D\u00e9put\u00e9", "gouvernementRef": {"@xmlns:xsi": "http://www.w3.org/2001/XMLSchema-instance", "@xsi:nil": "true"}, "acteurRef": "PA793508", "groupePolitiqueRef": "PO800508", "auteurRapporteurOrganeRef": {"@xmlns:xsi": "http://www.w3.org/2001/XMLSchema-instance", "@xsi:nil": "true"}}, "cosignataires": {"acteurRef": ["PA266793", "PA718884", "PA342240", "PA608416", "PA795406", "PA794178", "PA793094", "PA722390", "PA793476", "PA608826"]}, "suffixe": {"@xmlns:xsi": "http://www.w3.org/2001/XMLSchema-instance", "@xsi:nil": "true"}, "libelle": "M.&#160;Brigand,  M.&#160;Bony, Mme&#160;Bazin-Malgras, M.&#160;Bourgeaux, M.&#160;Hetzel, Mme&#160;P&#233;rigault, M.&#160;Taite, M.&#160;Ray, Mme&#160;Corneloup, M.&#160;Dubois et Mme&#160;Duby-Muller"}, "pointeurFragmentTexte": {"partieAmendableRef": {"@xmlns:xsi": "http://www.w3.org/2001/XMLSchema-instance", "@xsi:nil": "true"}, "division": {"titre": "Article 14", "articleDesignationCourte": "ART. 14", "articleDesignation": "ARTICLE 14", "type": "ARTICLE", "avant_A_Apres": "A", "divisionRattachee": {"@xmlns:xsi": "http://www.w3.org/2001/XMLSchema-instance", "@xsi:nil": "true"}, "articleAdditionnel": "false", "chapitreAdditionnel": "false", "urlDivisionTexteVise": "/16/textes/2436.asp#D_Article_14"}, "amendementStandard": {"alinea": {"avant_A_Apres": {"@xmlns:xsi": "http://www.w3.org/2001/XMLSchema-instance", "@xsi:nil": "true"}, "numero": "27", "alineaDesignation": "Alin\u00e9a 27"}}}, "corps": {"cartoucheInformatif": {"@xmlns:xsi": "http://www.w3.org/2001/XMLSchema-instance", "@xsi:nil": "true"}, "contenuAuteur": {"dispositif": "<p style=\"text-align: justify;\">Supprimer l'alin&#x00E9;a 27. </p>", "avantAppel": {"@xmlns:xsi": "http://www.w3.org/2001/XMLSchema-instance", "@xsi:nil": "true"}, "exposeSommaire": "<p style=\"text-align: justify;\">L&#x2019;amendement a pour but de supprimer la possibilit&#x00E9;, pour l&#x2019;autorit&#x00E9; comp&#x00E9;tente, d&#x2019;ajouter des prescriptions compl&#x00E9;mentaires pour le p&#x00E9;titionnaire.</p><p>En effet, ces alin&#x00E9;as ajoutent des contraintes qui ne sont aujourd&#x2019;hui pas pr&#x00E9;sentes dans l'ensemble des r&#x00E8;glementations qui encadrent les haies.</p><p>En outre, cette nouvelle section sur la protection des haies pr&#x00E9;voit d&#x2019;ores et d&#x00E9;j&#x00E0; que l&#x2019;autorit&#x00E9; comp&#x00E9;tente pourra demander des &#x00E9;l&#x00E9;ments compl&#x00E9;mentaires au dossier si besoin et ajouter, si n&#x00E9;cessaire, des prescriptions.</p>", "annexeExposeSommaire": {"@xmlns:xsi": "http://www.w3.org/2001/XMLSchema-instance", "@xsi:nil": "true"}}}, "cycleDeVie": {"dateDepot": "2024-04-23", "datePublication": "2024-05-01", "soumisArticle40": "false", "etatDesTraitements": {"etat": {"code": "DI", "libelle": "Discut\u00e9"}, "sousEtat": {"code": "DI", "libelle": "Rejet\u00e9"}}, "dateSort": "2024-05-04T12:28:57+02:00", "sort": "Rejet\u00e9"}, "representations": {"representation": {"nom": "PDF", "typeMime": {"type": "application", "subType": "PDF"}, "statutRepresentation": {"verbatim": "true", "canonique": "true", "officielle": "true", "transcription": "false", "enregistrement": "false"}, "repSource": {"@xmlns:xsi": "http://www.w3.org/2001/XMLSchema-instance", "@xsi:nil": "true"}, "offset": {"@xmlns:xsi": "http://www.w3.org/2001/XMLSchema-instance", "@xsi:nil": "true"}, "contenu": {"documentURI": "/base/AMANR5L16PO419610B2436P0D1N000840?format=pdf"}, "dateDispoRepresentation": {"@xmlns:xsi": "http://www.w3.org/2001/XMLSchema-instance", "@xsi:nil": "true"}}}, "seanceDiscussionRef": {"@xmlns:xsi": "http://www.w3.org/2001/XMLSchema-instance", "@xsi:nil": "true"}, "article99": "false", "loiReference": {"codeLoi": "s27", "divisionCodeLoi": {"@xmlns:xsi": "http://www.w3.org/2001/XMLSchema-instance", "@xsi:nil": "true"}}, "discussionCommune": {"@xmlns:xsi": "http://www.w3.org/2001/XMLSchema-instance", "@xsi:nil": "true"}, "discussionIdentique": {"@xmlns:xsi": "http://www.w3.org/2001/XMLSchema-instance", "@xsi:nil": "true"}, "accordGouvernementDepotHorsDelai": "Sans objet"}}