{"amendement": {"@xmlns": "http://schemas.assemblee-nationale.fr/referentiel", "uid": "AMANR5L16PO419865B2436P0D1N000819", "chronotag": "1714433145381", "legislature": "16", "identification": {"numeroLong": "CD819", "numeroOrdreDepot": "819", "prefixeOrganeExamen": "CION-DVP", "numeroRect": "0"}, "examenRef": "EXANR5L16PO419865B2436P0D1", "texteLegislatifRef": "PRJLANR5L16B2436", "triAmendement": "kaaaaaaaaaaaaaaaaaaaaaaaaaaaaaaaaaaaaaaaaaaaaaaaaaci", "cardinaliteAmdtMultiples": "1", "amendementParentRef": {"@xmlns:xsi": "http://www.w3.org/2001/XMLSchema-instance", "@xsi:nil": "true"}, "signataires": {"auteur": {"typeAuteur": "D\u00e9put\u00e9", "gouvernementRef": {"@xmlns:xsi": "http://www.w3.org/2001/XMLSchema-instance", "@xsi:nil": "true"}, "acteurRef": "PA795362", "groupePolitiqueRef": "PO800526", "auteurRapporteurOrganeRef": {"@xmlns:xsi": "http://www.w3.org/2001/XMLSchema-instance", "@xsi:nil": "true"}}, "cosignataires": {"acteurRef": ["PA793664", "PA793780", "PA795454", "PA794008", "PA793980", "PA795010", "PA794022", "PA794146", "PA795636", "PA795794", "PA793708", "PA794154", "PA794778", "PA795076", "PA610002", "PA795808", "PA720952", "PA736201", "PA793948"]}, "suffixe": {"@xmlns:xsi": "http://www.w3.org/2001/XMLSchema-instance", "@xsi:nil": "true"}, "libelle": "Mme&#160;Belluco,  Mme&#160;Pochon, Mme&#160;Arrighi, M.&#160;Ben&#160;Cheikh, Mme&#160;Chatelain, M.&#160;Fournier, Mme&#160;Garin, M.&#160;Iordanoff, Mme&#160;Laernoes, M.&#160;Lucas-Lundy, Mme&#160;Pasquini, M.&#160;Peytavie, M.&#160;Raux, Mme&#160;Regol, Mme&#160;Rousseau, Mme&#160;Sas, Mme&#160;Sebaihi, M.&#160;Tach&#233;, Mme&#160;Taill&#233;-Polian et M.&#160;Thierry"}, "pointeurFragmentTexte": {"partieAmendableRef": {"@xmlns:xsi": "http://www.w3.org/2001/XMLSchema-instance", "@xsi:nil": "true"}, "division": {"titre": "Article 15", "articleDesignationCourte": "ART. 15", "articleDesignation": "ARTICLE 15", "type": "ARTICLE", "avant_A_Apres": "A", "divisionRattachee": {"@xmlns:xsi": "http://www.w3.org/2001/XMLSchema-instance", "@xsi:nil": "true"}, "articleAdditionnel": "false", "chapitreAdditionnel": "false", "urlDivisionTexteVise": "/16/textes/2436.asp#D_Article_15"}, "amendementStandard": {"alinea": {"avant_A_Apres": {"@xmlns:xsi": "http://www.w3.org/2001/XMLSchema-instance", "@xsi:nil": "true"}, "numero": "30", "alineaDesignation": "Alin\u00e9a 30"}}}, "corps": {"cartoucheInformatif": {"@xmlns:xsi": "http://www.w3.org/2001/XMLSchema-instance", "@xsi:nil": "true"}, "contenuAuteur": {"dispositif": "<p style=\"text-align: justify;\">&#x00C0; l&#x2019;alin&#x00E9;a&nbsp;30, substituer aux mots&nbsp;:</p><p style=\"text-align: justify;\">&#x00AB;&nbsp;de la date d&#x2019;entr&#x00E9;e en vigueur de la pr&#x00E9;sente loi&nbsp;&#x00BB;</p><p style=\"text-align: justify;\">les mots&nbsp;:</p><p style=\"text-align: justify;\">&#x00AB;&nbsp;du 1<sup>er</sup> janvier 2027&nbsp;&#x00BB;.</p>", "avantAppel": {"@xmlns:xsi": "http://www.w3.org/2001/XMLSchema-instance", "@xsi:nil": "true"}, "exposeSommaire": "<p style=\"text-align: justify;\">L'objet de cet amendement de repli par rapport &#x00E0; une suppression de l'article est de reporter la mise en &#x0153;uvre de cette modification l&#x00E9;gislative.&nbsp;</p><p style=\"text-align: justify;\">Premi&#x00E8;rement, les proc&#x00E9;dures de contentieux ont largement &#x00E9;volu&#x00E9; depuis le d&#x00E9;but de la mandature, et m&#x00E9;ritent d'&#x00EA;tre &#x00E9;valu&#x00E9;s. Ce travail doit &#x00EA;tre fait avant l'entr&#x00E9;e en vigueur de nouvelles modifications.&nbsp;</p><p style=\"text-align: justify;\">Deuxi&#x00E8;mement, ces alin&#x00E9;as permettraient d'appliquer de nouvelles r&#x00E8;gles &#x00E0; des litiges en cours, ce qui complexifie encore davantage les modalit&#x00E9;s de contentieux, rendant les proc&#x00E9;dures &#x00E9;volutives.&nbsp;</p>", "annexeExposeSommaire": {"@xmlns:xsi": "http://www.w3.org/2001/XMLSchema-instance", "@xsi:nil": "true"}}}, "cycleDeVie": {"dateDepot": "2024-04-28", "datePublication": "2024-04-29", "soumisArticle40": "false", "etatDesTraitements": {"etat": {"code": "DI", "libelle": "Discut\u00e9"}, "sousEtat": {"code": "DI", "libelle": "Rejet\u00e9"}}, "dateSort": "2024-04-30T01:25:27+02:00", "sort": "Rejet\u00e9"}, "representations": {"representation": {"nom": "PDF", "typeMime": {"type": "application", "subType": "PDF"}, "statutRepresentation": {"verbatim": "true", "canonique": "true", "officielle": "true", "transcription": "false", "enregistrement": "false"}, "repSource": {"@xmlns:xsi": "http://www.w3.org/2001/XMLSchema-instance", "@xsi:nil": "true"}, "offset": {"@xmlns:xsi": "http://www.w3.org/2001/XMLSchema-instance", "@xsi:nil": "true"}, "contenu": {"documentURI": "/base/AMANR5L16PO419865B2436P0D1N000819?format=pdf"}, "dateDispoRepresentation": {"@xmlns:xsi": "http://www.w3.org/2001/XMLSchema-instance", "@xsi:nil": "true"}}}, "seanceDiscussionRef": {"@xmlns:xsi": "http://www.w3.org/2001/XMLSchema-instance", "@xsi:nil": "true"}, "article99": "false", "loiReference": {"@xmlns:xsi": "http://www.w3.org/2001/XMLSchema-instance", "@xsi:nil": "true"}, "discussionCommune": {"@xmlns:xsi": "http://www.w3.org/2001/XMLSchema-instance", "@xsi:nil": "true"}, "discussionIdentique": {"@xmlns:xsi": "http://www.w3.org/2001/XMLSchema-instance", "@xsi:nil": "true"}, "accordGouvernementDepotHorsDelai": "Sans objet"}}