{"amendement": {"@xmlns": "http://schemas.assemblee-nationale.fr/referentiel", "uid": "AMANR5L16PO419610B2436P0D1N002980", "chronotag": "1714770263389", "legislature": "16", "identification": {"numeroLong": "CE2980", "numeroOrdreDepot": "2980", "prefixeOrganeExamen": "CION-ECO", "numeroRect": "0"}, "examenRef": "EXANR5L16PO419610B2436P0D1", "texteLegislatifRef": "PRJLANR5L16B2436", "triAmendement": "faaaaaaaaaaaaaaaaaaaaaaaaaaaaaaaaaaaaaaaaaaaaaaaaapfvri", "cardinaliteAmdtMultiples": "1", "amendementParentRef": {"@xmlns:xsi": "http://www.w3.org/2001/XMLSchema-instance", "@xsi:nil": "true"}, "signataires": {"auteur": {"typeAuteur": "D\u00e9put\u00e9", "gouvernementRef": {"@xmlns:xsi": "http://www.w3.org/2001/XMLSchema-instance", "@xsi:nil": "true"}, "acteurRef": "PA793664", "groupePolitiqueRef": "PO800526", "auteurRapporteurOrganeRef": {"@xmlns:xsi": "http://www.w3.org/2001/XMLSchema-instance", "@xsi:nil": "true"}}, "cosignataires": {"@xmlns:xsi": "http://www.w3.org/2001/XMLSchema-instance", "@xsi:nil": "true"}, "suffixe": "et les membres du groupe \u00c9cologiste - NUPES", "libelle": "Mme&#160;Pochon et les membres du groupe &#201;cologiste - NUPES"}, "pointeurFragmentTexte": {"partieAmendableRef": {"@xmlns:xsi": "http://www.w3.org/2001/XMLSchema-instance", "@xsi:nil": "true"}, "division": {"titre": "Article 10", "articleDesignationCourte": "ART. 10", "articleDesignation": "ARTICLE 10", "type": "ARTICLE", "avant_A_Apres": "A", "divisionRattachee": {"@xmlns:xsi": "http://www.w3.org/2001/XMLSchema-instance", "@xsi:nil": "true"}, "articleAdditionnel": "false", "chapitreAdditionnel": "false", "urlDivisionTexteVise": "/16/textes/2436.asp#D_Article_10"}, "amendementStandard": {"alinea": {"avant_A_Apres": {"@xmlns:xsi": "http://www.w3.org/2001/XMLSchema-instance", "@xsi:nil": "true"}, "numero": "18", "alineaDesignation": "Alin\u00e9a 18"}}}, "corps": {"cartoucheInformatif": {"@xmlns:xsi": "http://www.w3.org/2001/XMLSchema-instance", "@xsi:nil": "true"}, "contenuAuteur": {"dispositif": "<p style=\"text-align: justify;\">I.&#x2013; Compl&#x00E9;ter l&#x2019;alin&#x00E9;a&nbsp;18 par la phrase suivante&nbsp;:</p><p style=\"text-align: justify;\">&#x00AB;&nbsp;&#x00C0; ce titre, elle publie annuellement un bilan de son action sur la base d&#x2019;indicateurs d&#x00E9;finis par d&#x00E9;cret apr&#x00E8;s avis d&#x2019;une instance nationale de pilotage de la politique d&#x2019;installation et de transmission.&nbsp;&#x00BB;</p><p style=\"text-align: justify;\">II &#x2013; &#x00C0; l&#x2019;alin&#x00E9;a&nbsp;20, apr&#x00E8;s la r&#x00E9;f&#x00E9;rence&nbsp;:</p><p style=\"text-align: justify;\">&#x00AB;&nbsp;L.&nbsp;511&#x2011;4&nbsp;&#x00BB;,</p><p style=\"text-align: justify;\">ins&#x00E9;rer les mots&nbsp;:</p><p style=\"text-align: justify;\">&#x00AB;&nbsp;, en publie annuellement un bilan sur la base d&#x2019;indicateurs d&#x00E9;finis par d&#x00E9;cret apr&#x00E8;s avis d&#x2019;une instance nationale de pilotage de la politique d&#x2019;installation et de transmission&nbsp;&#x00BB;.</p>", "avantAppel": {"@xmlns:xsi": "http://www.w3.org/2001/XMLSchema-instance", "@xsi:nil": "true"}, "exposeSommaire": "<p style=\"text-align: justify;\">Cet amendement propose de renforcer le cadre l&#x00E9;gislatif applicable aux dispositifs de suivi de la mise en &#x0153;uvre de la politique d&#x2019;installation et de transmission en agriculture dans le cadre des missions confi&#x00E9;es aux chambres d&#x2019;agriculture.&nbsp;</p><p>En effet, &nbsp;le suivi de cette politique est actuellement mal document&#x00E9;&nbsp;&#x00E0; la fois au niveau national o&#x00F9; Chambre d&#x2019;agriculture France ne publie que peu d&#x2019;&#x00E9;l&#x00E9;ments et plus encore au niveau local avec de fortes disparit&#x00E9;s sur les &#x00E9;l&#x00E9;ments disponibles pour objectiver cette politique.&nbsp;</p><p>Il est n&#x00E9;anmoins &#x00E9;tabli qu&#x2019;une importante proportion de candidats &#x00E0; l&#x2019;installation&nbsp;abandonnent en cours de route (rapport du&nbsp;CGAEER, de la cour des Comptes) avec un delta d&#x2019;&#x2153; entre les personnes se pr&#x00E9;sentant au PAI en moyenne chaque ann&#x00E9;e, et le nombre moyen d&#x2019;installation.</p><p>Ce suivi fin est d&#x2019;autant plus important que la mise en place du point d&#x2019;accueil d&#x00E9;partemental unique et du r&#x00E9;seau France services agriculture vont modifier en profondeur le parcours &#x00E0; l&#x2019;installation.&nbsp;</p><p>Ainsi, il est propos&#x00E9; que Chambres d&#x2019;agriculture France comme les chambres d&#x00E9;partementales et r&#x00E9;gionales d&#x2019;agriculture&nbsp;publient annuellement un bilan des actions men&#x00E9;es &#x00E0; leur &#x00E9;chelle et dans le cadre de leur mission. Ce bilan serait construit sur la base d&#x2019;indicateurs standardis&#x00E9;s pour en faciliter le suivi et d&#x00E9;finis par d&#x00E9;cret apr&#x00E8;s avis de l&#x2019;instance nationale associ&#x00E9;e &#x00E0; la gouvernance de la politique d&#x2019;installation et de transmission en agriculture. Enfin, il est propos&#x00E9; que les chambres d&#x2019;agriculture d&#x00E9;partementales rendent compte de leur action notamment quant &#x00E0; la mise en &#x0153;uvre du point d&#x2019;accueil d&#x00E9;partemental unique &#x00E0; des<br>instances de pilotage d&#x00E9;partementales associant l'ensemble des parties concern&#x00E9;es.</p><p>Cet amendement est propos&#x00E9; par la FADEAR, le R&#x00E9;seau CIVAM, la F&#x00E9;d&#x00E9;ration Nationale d&#x2019;Agriculture Biologique, le Mouvement Inter-R&#x00E9;gional des AMAP, le RENETA, SOL, et Terre de Liens, membres du Collectif Nourrir. Aux c&#x00F4;t&#x00E9;s des chambres d'agriculture, ces organisations repr&#x00E9;sentent des acteurs diversifi&#x00E9;s et compl&#x00E9;mentaires participant activement au pilotage et la mise en &#x0153;uvre des politiques et dispositifs d&#x2019;accompagnement &#x00E0; l&#x2019;installation-transmission, en accompagnant aujourd&#x2019;hui plus de 10 000 candidats et 2 000 c&#x00E9;dants par an, avec &#x00E0; la cl&#x00E9; plus d&#x2019;un tiers des installations annuelles.</p><p>&nbsp;</p>", "annexeExposeSommaire": {"@xmlns:xsi": "http://www.w3.org/2001/XMLSchema-instance", "@xsi:nil": "true"}}}, "cycleDeVie": {"dateDepot": "2024-04-26", "datePublication": "2024-04-29", "soumisArticle40": "false", "etatDesTraitements": {"etat": {"code": "DI", "libelle": "Discut\u00e9"}, "sousEtat": {"code": "DI", "libelle": "Rejet\u00e9"}}, "dateSort": "2024-05-03T23:04:10+02:00", "sort": "Rejet\u00e9"}, "representations": {"representation": {"nom": "PDF", "typeMime": {"type": "application", "subType": "PDF"}, "statutRepresentation": {"verbatim": "true", "canonique": "true", "officielle": "true", "transcription": "false", "enregistrement": "false"}, "repSource": {"@xmlns:xsi": "http://www.w3.org/2001/XMLSchema-instance", "@xsi:nil": "true"}, "offset": {"@xmlns:xsi": "http://www.w3.org/2001/XMLSchema-instance", "@xsi:nil": "true"}, "contenu": {"documentURI": "/base/AMANR5L16PO419610B2436P0D1N002980?format=pdf"}, "dateDispoRepresentation": {"@xmlns:xsi": "http://www.w3.org/2001/XMLSchema-instance", "@xsi:nil": "true"}}}, "seanceDiscussionRef": {"@xmlns:xsi": "http://www.w3.org/2001/XMLSchema-instance", "@xsi:nil": "true"}, "article99": "false", "loiReference": {"@xmlns:xsi": "http://www.w3.org/2001/XMLSchema-instance", "@xsi:nil": "true"}, "discussionCommune": {"@xmlns:xsi": "http://www.w3.org/2001/XMLSchema-instance", "@xsi:nil": "true"}, "discussionIdentique": {"@xmlns:xsi": "http://www.w3.org/2001/XMLSchema-instance", "@xsi:nil": "true"}, "accordGouvernementDepotHorsDelai": "Sans objet"}}